quick_cli/__init__.py
quick_cli/action_wrapper.py
quick_cli/actions.py
quick_cli/actions_test.py
quick_cli/app.py
quick_cli/app_info.py
quick_cli/app_info_test.py
quick_cli/context.py
quick_cli/quick_cli_test.py
QuickCLI-0.2.2.dist-info/LICENSE
QuickCLI-0.2.2.dist-info/METADATA
QuickCLI-0.2.2.dist-info/WHEEL
QuickCLI-0.2.2.dist-info/top_level.txt
QuickCLI-0.2.2.dist-info/RECORD
