Metadata-Version: 2.1
Name: QuickCLI
Version: 0.2.2
Summary: Quick and Painless Python CLI Building
Home-page: https://mlasevich.github.io/QuickCLI/
Author: Michael Lasevich
Author-email: mlasevich+quickcli@gmail.com
License: Apache 2.0
Platform: UNKNOWN
Classifier: Programming Language :: Python :: 3
Classifier: Programming Language :: Python :: 2.7
Classifier: License :: OSI Approved :: Apache Software License
Classifier: Operating System :: OS Independent
Requires-Dist: PyYaml
Requires-Dist: future
